streamlit_deckgl/__init__.py
streamlit_deckgl/frontend/index.html
streamlit_deckgl/frontend/main.js
streamlit_deckgl/frontend/streamlit-component-lib.js
streamlit_deckgl/frontend/style.css
streamlit_deckgl-0.5.1.dist-info/LICENSE
streamlit_deckgl-0.5.1.dist-info/METADATA
streamlit_deckgl-0.5.1.dist-info/WHEEL
streamlit_deckgl-0.5.1.dist-info/top_level.txt
streamlit_deckgl-0.5.1.dist-info/RECORD
