Metadata-Version: 2.1
Name: streamlit-deckgl
Version: 0.5.1
Summary: Streamlit component for deck.gl visualisation
Author: Oceanum
Author-email: developers@oceanum.science
Keywords: streamlit,pydeck,deck.gl,visualisation
Requires-Python: >=3.7
License-File: LICENSE
Requires-Dist: streamlit (>=1.2)
Requires-Dist: jinja2
Requires-Dist: pydeck (>=0.8)
